sos_ruta/__init__.py
sos_ruta/_version.py
sos_ruta/kernel.py
sos_ruta-0.1.dist-info/LICENSE
sos_ruta-0.1.dist-info/METADATA
sos_ruta-0.1.dist-info/NOTICE
sos_ruta-0.1.dist-info/WHEEL
sos_ruta-0.1.dist-info/entry_points.txt
sos_ruta-0.1.dist-info/top_level.txt
sos_ruta-0.1.dist-info/RECORD
