Metadata-Version: 2.1
Name: sos-ruta
Version: 0.1
Summary: SoS Notebook extension for the language Apache UIMA Ruta
Home-page: UNKNOWN
Author: Averbis
License: Apache License, Version 2.0. Copyright Averbis GmbH
Platform: UNKNOWN
Classifier: Development Status :: 4 - Beta
Classifier: Environment :: Console
Classifier: License :: OSI Approved :: Apache Software License
Classifier: Natural Language :: English
Classifier: Operating System :: POSIX :: Linux
Classifier: Operating System :: MacOS :: MacOS X
Classifier: Operating System :: Microsoft :: Windows
Classifier: Intended Audience :: Information Technology
Classifier: Intended Audience :: Science/Research
Classifier: Programming Language :: Python :: 3 :: Only
Classifier: Programming Language :: Python :: Implementation :: CPython
Requires-Dist: sos (>=0.19.8)
Requires-Dist: sos-notebook (>=0.19.4)
Requires-Dist: dkpro-cassis (>=0.5.1)
